pytest_canonical_data/__init__.py
pytest_canonical_data/canonical_data.py
pytest_canonical_data/drivers.py
pytest_canonical_data/exceptions.py
pytest_canonical_data/plugin.py
pytest_canonical_data-0.1.0.dist-info/LICENSE
pytest_canonical_data-0.1.0.dist-info/METADATA
pytest_canonical_data-0.1.0.dist-info/WHEEL
pytest_canonical_data-0.1.0.dist-info/entry_points.txt
pytest_canonical_data-0.1.0.dist-info/top_level.txt
pytest_canonical_data-0.1.0.dist-info/RECORD
