Metadata-Version: 2.1
Name: pytest-canonical-data
Version: 0.1.0
Summary: A plugin which allows to compare results with canonical results, based on previous runs
Home-page: https://github.com/shuternay/pytest-canonical-data
Author: Sergey Kiselev
Author-email: kiselev.sg@gmail.com
Maintainer: Sergey Kiselev
Maintainer-email: kiselev.sg@gmail.com
License: MIT
Platform: UNKNOWN
Classifier: Development Status :: 2 - Pre-Alpha
Classifier: Framework :: Pytest
Classifier: Intended Audience :: Developers
Classifier: Topic :: Software Development :: Testing
Classifier: Programming Language :: Python
Classifier: Programming Language :: Python :: 3
Classifier: Programming Language :: Python :: 3.5
Classifier: Programming Language :: Python :: 3.6
Classifier: Programming Language :: Python :: 3.7
Classifier: Programming Language :: Python :: 3.8
Classifier: Programming Language :: Python :: Implementation :: CPython
Classifier: Programming Language :: Python :: Implementation :: PyPy
Classifier: Operating System :: OS Independent
Classifier: License :: OSI Approved :: MIT License
Requires-Python: >=3.5
Requires-Dist: pytest (>=3.5.0)
